fastadk/__about__.py
fastadk/__init__.py
fastadk/adapters/__init__.py
fastadk/adapters/discord.py
fastadk/adapters/slack.py
fastadk/api/__init__.py
fastadk/api/models.py
fastadk/api/router.py
fastadk/api/streaming.py
fastadk/cli/__init__.py
fastadk/cli/main.py
fastadk/cli/repl.py
fastadk/core/__init__.py
fastadk/core/agent.py
fastadk/core/agent.pyi
fastadk/core/batch.py
fastadk/core/cache.py
fastadk/core/config.py
fastadk/core/context.py
fastadk/core/context_policy.py
fastadk/core/exceptions.py
fastadk/core/orchestration.py
fastadk/core/plugin.py
fastadk/core/plugin_manager.py
fastadk/core/property_types.py
fastadk/core/retry.py
fastadk/core/summarization.py
fastadk/core/tool_manager.py
fastadk/core/workflow.py
fastadk/memory/__init__.py
fastadk/memory/base.py
fastadk/memory/inmemory.py
fastadk/memory/redis.py
fastadk/memory/vector.py
fastadk/observability/__init__.py
fastadk/observability/logger.py
fastadk/observability/metrics.py
fastadk/observability/redaction.py
fastadk/observability/tracing.py
fastadk/providers/__init__.py
fastadk/providers/base.py
fastadk/providers/factory.py
fastadk/providers/gemini.py
fastadk/providers/litellm.py
fastadk/providers/openai.py
fastadk/testing/__init__.py
fastadk/testing/mock_tools.py
fastadk/testing/utils.py
fastadk/tokens/__init__.py
fastadk/tokens/counting.py
fastadk/tokens/models.py
fastadk/tokens/pricing.py
fastadk/tokens/utils.py
fastadk/training/__init__.py
fastadk/training/fine_tuning.py
fastadk-0.2.0.dist-info/METADATA
fastadk-0.2.0.dist-info/WHEEL
fastadk-0.2.0.dist-info/entry_points.txt
fastadk-0.2.0.dist-info/licenses/LICENSE
fastadk-0.2.0.dist-info/RECORD
