Metadata-Version: 2.4
Name: fastadk
Version: 0.2.0
Summary: A developer-friendly framework for building AI agents with Google ADK
Project-URL: Homepage, https://github.com/fastadk/fastadk
Project-URL: Documentation, https://docs.fastadk.dev
Project-URL: Repository, https://github.com/fastadk/fastadk
Project-URL: Bug Tracker, https://github.com/fastadk/fastadk/issues
Project-URL: Discussions, https://github.com/fastadk/fastadk/discussions
Project-URL: Discord, https://discord.gg/fastadk
Author-email: FastADK Team <team@fastadk.dev>
Maintainer-email: FastADK Team <team@fastadk.dev>
License: MIT
License-File: LICENSE
Keywords: agents,ai,artificial-intelligence,automation,chatbots,framework,google-adk,llm
Classifier: Development Status :: 3 - Alpha
Classifier: Intended Audience :: Developers
Classifier: License :: OSI Approved :: MIT License
Classifier: Programming Language :: Python :: 3
Classifier: Programming Language :: Python :: 3.10
Classifier: Programming Language :: Python :: 3.11
Classifier: Programming Language :: Python :: 3.12
Classifier: Topic :: Scientific/Engineering :: Artificial Intelligence
Classifier: Topic :: Software Development :: Libraries :: Python Modules
Requires-Python: >=3.10
Requires-Dist: aioconsole>=0.8.1
Requires-Dist: aiofiles>=23.0.0
Requires-Dist: anthropic>=0.56.0
Requires-Dist: asyncio-redis>=0.16.0
Requires-Dist: fastapi>=0.104.0
Requires-Dist: google-generativeai>=0.8.5
Requires-Dist: httpx>=0.25.0
Requires-Dist: litellm>=1.74.0
Requires-Dist: loguru>=0.7.0
Requires-Dist: mkdocs-material>=9.6.15
Requires-Dist: mkdocstrings-python>=1.16.12
Requires-Dist: openai>=1.93.0
Requires-Dist: opentelemetry-api>=1.34.1
Requires-Dist: opentelemetry-exporter-otlp>=1.34.1
Requires-Dist: opentelemetry-instrumentation-fastapi>=0.55b1
Requires-Dist: opentelemetry-sdk>=1.34.1
Requires-Dist: prometheus-client>=0.17.0
Requires-Dist: pydantic-settings>=2.0.0
Requires-Dist: pydantic>=2.5.0
Requires-Dist: pylint>=3.3.7
Requires-Dist: python-dotenv>=1.1.1
Requires-Dist: pyyaml>=6.0
Requires-Dist: reddis>=1.0.1
Requires-Dist: rich>=14.0.0
Requires-Dist: streamlit>=1.46.1
Requires-Dist: tiktoken>=0.5.0
Requires-Dist: tomli>=2.0.1
Requires-Dist: typer>=0.9.0
Requires-Dist: types-pyyaml>=6.0.12.20250516
Requires-Dist: types-requests>=2.32.4.20250611
Requires-Dist: uvicorn[standard]>=0.24.0
Provides-Extra: all
Requires-Dist: aioredis>=2.0.0; extra == 'all'
Requires-Dist: anthropic>=0.5.0; extra == 'all'
Requires-Dist: authlib>=1.2.0; extra == 'all'
Requires-Dist: black>=23.7.0; extra == 'all'
Requires-Dist: chromadb>=0.4.0; extra == 'all'
Requires-Dist: cryptography>=41.0.0; extra == 'all'
Requires-Dist: google-cloud-firestore>=2.13.0; extra == 'all'
Requires-Dist: google-cloud-logging>=3.8.0; extra == 'all'
Requires-Dist: google-cloud-storage>=2.10.0; extra == 'all'
Requires-Dist: httpx>=0.25.0; extra == 'all'
Requires-Dist: mypy>=1.5.0; extra == 'all'
Requires-Dist: openai>=1.0.0; extra == 'all'
Requires-Dist: opentelemetry-api>=1.20.0; extra == 'all'
Requires-Dist: opentelemetry-instrumentation-fastapi>=0.41b0; extra == 'all'
Requires-Dist: opentelemetry-sdk>=1.20.0; extra == 'all'
Requires-Dist: pinecone-client>=2.2.0; extra == 'all'
Requires-Dist: pre-commit>=3.4.0; extra == 'all'
Requires-Dist: prometheus-client>=0.17.0; extra == 'all'
Requires-Dist: pytest-asyncio>=0.21.0; extra == 'all'
Requires-Dist: pytest-cov>=4.1.0; extra == 'all'
Requires-Dist: pytest>=7.4.0; extra == 'all'
Requires-Dist: python-jose[cryptography]>=3.3.0; extra == 'all'
Requires-Dist: redis[hiredis]>=5.0.0; extra == 'all'
Requires-Dist: ruff>=0.0.287; extra == 'all'
Requires-Dist: tiktoken>=0.5.0; extra == 'all'
Provides-Extra: anthropic
Requires-Dist: anthropic>=0.5.0; extra == 'anthropic'
Provides-Extra: cloud
Requires-Dist: google-cloud-logging>=3.8.0; extra == 'cloud'
Requires-Dist: google-cloud-storage>=2.10.0; extra == 'cloud'
Provides-Extra: dev
Requires-Dist: black>=23.7.0; extra == 'dev'
Requires-Dist: httpx>=0.25.0; extra == 'dev'
Requires-Dist: mypy>=1.5.0; extra == 'dev'
Requires-Dist: pre-commit>=3.4.0; extra == 'dev'
Requires-Dist: pytest-asyncio>=0.21.0; extra == 'dev'
Requires-Dist: pytest-cov>=4.1.0; extra == 'dev'
Requires-Dist: pytest>=7.4.0; extra == 'dev'
Requires-Dist: ruff>=0.0.287; extra == 'dev'
Provides-Extra: enterprise
Requires-Dist: authlib>=1.2.0; extra == 'enterprise'
Requires-Dist: cryptography>=41.0.0; extra == 'enterprise'
Requires-Dist: python-jose[cryptography]>=3.3.0; extra == 'enterprise'
Provides-Extra: firestore
Requires-Dist: google-cloud-firestore>=2.13.0; extra == 'firestore'
Provides-Extra: observability
Requires-Dist: opentelemetry-api>=1.20.0; extra == 'observability'
Requires-Dist: opentelemetry-instrumentation-fastapi>=0.41b0; extra == 'observability'
Requires-Dist: opentelemetry-sdk>=1.20.0; extra == 'observability'
Requires-Dist: prometheus-client>=0.17.0; extra == 'observability'
Requires-Dist: tiktoken>=0.5.0; extra == 'observability'
Provides-Extra: openai
Requires-Dist: openai>=1.0.0; extra == 'openai'
Provides-Extra: redis
Requires-Dist: aioredis>=2.0.0; extra == 'redis'
Requires-Dist: redis[hiredis]>=5.0.0; extra == 'redis'
Provides-Extra: vector
Requires-Dist: chromadb>=0.4.0; extra == 'vector'
Requires-Dist: pinecone-client>=2.2.0; extra == 'vector'
